MANIFEST.in
setup.py
twitter_controller/Person.py
twitter_controller/PersonAnalyzer.py
twitter_controller/Plotter.py
twitter_controller/Text.py
twitter_controller/TwitterDownloader.py
twitter_controller/__init__.py
twitter_controller.egg-info/PKG-INFO
twitter_controller.egg-info/SOURCES.txt
twitter_controller.egg-info/dependency_links.txt
twitter_controller.egg-info/not-zip-safe
twitter_controller.egg-info/requires.txt
twitter_controller.egg-info/top_level.txt
twitter_controller/resources/NotTrustedSources
twitter_controller/resources/TrustedSources