Metadata-Version: 1.0
Name: twitter-controller
Version: 0.7
Summary: This is a package to analyze tweets of a certain person
Home-page: https://github.com/AGHPythonCourse2017/zad3-kanes115.git
Author: Dominik Stanaszek
Author-email: dominikstanaszek@icloud.com
License: NONE
Platform: UNKNOWN
